CHANGELOG.txt
LICENSE.txt
MANIFEST.in
README.txt
setup.py
testlib_pndmev/__init__.py
testlib_pndmev.egg-info/PKG-INFO
testlib_pndmev.egg-info/SOURCES.txt
testlib_pndmev.egg-info/dependency_links.txt
testlib_pndmev.egg-info/top_level.txt