Metadata-Version: 1.1
Name: testlib-pndmev
Version: 0.0.3
Summary: Test library
Home-page: UNKNOWN
Author: Diam Pan
Author-email: pndmev@gmail.com
License: MIT
Keywords: test
Platform: UNKNOWN
Classifier: Development Status :: 5 - Production/Stable
Classifier: Intended Audience :: Education
Classifier: Operating System :: Microsoft :: Windows :: Windows 10
Classifier: License :: OSI Approved :: MIT License
Classifier: Programming Language :: Python :: 3
